tests/__init__.py
tests/confighelper.py
tests/configuration.py
tests/tomaatti.py
tomaatti/__init__.py
tomaatti/cli.py
tomaatti/cli_config.py
tomaatti/internal/__init__.py
tomaatti/internal/confighelper.py
tomaatti/internal/configuration.py
tomaatti/internal/experimental.py
tomaatti/internal/i3buttonidentifier.py
tomaatti/internal/i3integration.py
tomaatti/internal/timertype.py
tomaatti/internal/tomaatti.py
tomaatti-0.5.0.dist-info/LICENSE.md
tomaatti-0.5.0.dist-info/METADATA
tomaatti-0.5.0.dist-info/WHEEL
tomaatti-0.5.0.dist-info/entry_points.txt
tomaatti-0.5.0.dist-info/top_level.txt
tomaatti-0.5.0.dist-info/RECORD
