Metadata-Version: 2.1
Name: tomaatti
Version: 0.5.0
Summary: Pomodoro timer with i3 integration
Home-page: https://github.com/thuetz/i3-tomaatti
Author: Tim Hütz
Author-email: tim@huetz.biz
License: GPL-3.0
Platform: Linux
Classifier: Programming Language :: Python
Classifier: Programming Language :: Python :: 3
Classifier: Programming Language :: Python :: 3.4
Classifier: Programming Language :: Python :: 3.5
Classifier: Programming Language :: Python :: 3.6
Classifier: License :: OSI Approved :: GNU General Public License v3 (GPLv3)
Classifier: Environment :: X11 Applications
Classifier: Topic :: Desktop Environment :: Window Managers
Classifier: Topic :: Utilities
Classifier: Development Status :: 3 - Alpha
Requires-Dist: easygui
